azure/cli/core/__init__.py
azure/cli/core/_breaking_change.py
azure/cli/core/_completers.py
azure/cli/core/_config.py
azure/cli/core/_debug.py
azure/cli/core/_environment.py
azure/cli/core/_help.py
azure/cli/core/_help_loaders.py
azure/cli/core/_output.py
azure/cli/core/_profile.py
azure/cli/core/_session.py
azure/cli/core/api.py
azure/cli/core/azclierror.py
azure/cli/core/azlogging.py
azure/cli/core/breaking_change.py
azure/cli/core/cloud.py
azure/cli/core/command_recommender.py
azure/cli/core/credential_helper.py
azure/cli/core/decorators.py
azure/cli/core/file_util.py
azure/cli/core/intercept_survey.py
azure/cli/core/keys.py
azure/cli/core/local_context.py
azure/cli/core/mock.py
azure/cli/core/parser.py
azure/cli/core/style.py
azure/cli/core/telemetry.py
azure/cli/core/util.py
azure/cli/core/aaz/__init__.py
azure/cli/core/aaz/_arg.py
azure/cli/core/aaz/_arg_action.py
azure/cli/core/aaz/_arg_browser.py
azure/cli/core/aaz/_arg_fmt.py
azure/cli/core/aaz/_base.py
azure/cli/core/aaz/_client.py
azure/cli/core/aaz/_command.py
azure/cli/core/aaz/_command_ctx.py
azure/cli/core/aaz/_content_builder.py
azure/cli/core/aaz/_error_format.py
azure/cli/core/aaz/_field_type.py
azure/cli/core/aaz/_field_value.py
azure/cli/core/aaz/_help.py
azure/cli/core/aaz/_http_policy.py
azure/cli/core/aaz/_operation.py
azure/cli/core/aaz/_paging.py
azure/cli/core/aaz/_poller.py
azure/cli/core/aaz/_prompt.py
azure/cli/core/aaz/_selector.py
azure/cli/core/aaz/_utils.py
azure/cli/core/aaz/exceptions.py
azure/cli/core/aaz/utils.py
azure/cli/core/auth/__init__.py
azure/cli/core/auth/binary_cache.py
azure/cli/core/auth/constants.py
azure/cli/core/auth/credential_adaptor.py
azure/cli/core/auth/identity.py
azure/cli/core/auth/msal_credentials.py
azure/cli/core/auth/persistence.py
azure/cli/core/auth/util.py
azure/cli/core/auth/landing_pages/error.html
azure/cli/core/auth/landing_pages/success.html
azure/cli/core/commands/__init__.py
azure/cli/core/commands/arm.py
azure_cli_core-2.80.0.dist-info/licenses/LICENSE.txt
azure_cli_core-2.80.0.dist-info/METADATA
azure_cli_core-2.80.0.dist-info/WHEEL
azure_cli_core-2.80.0.dist-info/top_level.txt
azure_cli_core-2.80.0.dist-info/RECORD
